flake8_todos/__init__.py
flake8_todos/_checker.py
flake8_todos/_constants.py
flake8_todos/_error.py
flake8_todos/_rules.py
flake8_todos/_token.py
flake8_todos-0.3.1.dist-info/entry_points.txt
flake8_todos-0.3.1.dist-info/LICENSE
flake8_todos-0.3.1.dist-info/WHEEL
flake8_todos-0.3.1.dist-info/METADATA
flake8_todos-0.3.1.dist-info/RECORD
