Metadata-Version: 2.1
Name: flake8-todos
Version: 0.3.1
Summary: Python linter to check TODO comments for consistency and best practice.
Home-page: https://github.com/orsinium-labs/flake8-todos
License: BSD 3-Clause
Keywords: flake8 flake8-plugin linter styleguide code quality
Author: Gram
Author-email: gram@orsinium.dev
Requires-Python: >=3.8
Classifier: Development Status :: 4 - Beta
Classifier: Environment :: Console
Classifier: Framework :: Flake8
Classifier: Intended Audience :: Developers
Classifier: Operating System :: OS Independent
Classifier: Topic :: Software Development :: Libraries :: Python Modules
Classifier: Topic :: Software Development :: Quality Assurance
Classifier: License :: OSI Approved :: BSD License
Requires-Dist: flake8
Requires-Dist: pycodestyle
Requires-Dist: isort[pyproject] ; extra == "dev"
Requires-Dist: pytest ; extra == "dev"
Provides-Extra: dev
